{
  "title": "עדכון ביניים מוול סטריט 🇺🇸 – יום שני, 6.7.2026, 21:54",
  "date": "2026-07-06",
  "sections": [
    {
      "heading": "עדכון ביניים",
      "content": "* חברת Grab (GRAB): מנכ״ל Uber דארה חוסרושאהי פרש מדירקטוריון החברה. זהו שינוי ממשל תאגידי נקודתי בחברה שממוקדת בתחבורה, משלוחים ותשלומים בדרום-מזרח אסיה.\n* שוק העבודה בארה״ב: אינדיקציה נוספת מצביעה על חולשה מתחת לפני השטח, כאשר הפער בין צרכנים שאומרים שמשרות זמינות בשפע לבין כאלה שאומרים שקשה למצוא עבודה ירד ביוני ל-2.4 נקודות, הרמה הנמוכה מאז 2020. רק 24.9% אמרו שמשרות זמינות בשפע, מול 22.5% שאמרו שקשה למצוא עבודה, והמדד מצביע על סיכון לעלייה באבטלה עד 6.0% לעומת 4.2% כיום.\n* קרנות האנרגיה: נרשמה האצה ביציאת כספים מהסקטור, עם פדיונות של 3.2 מיליארד דולר מקרנות אנרגיה בשבוע שהסתיים ב-1 ביולי. זו המשיכה השבועית הגדולה מאז יולי 2024 והשנייה בגודלה בעשור לפחות, והממוצע ל-4 שבועות עבר ליציאות של 1.8 מיליארד דולר אחרי כניסות של 2.5 מיליארד דולר רק לפני חודשיים.\n* Appaloosa Management: לפי Bloomberg, הקרן של דיוויד טפר הניבה תשואה של 32% במחצית הראשונה של השנה. הקרן מנהלת 23 מיליארד דולר, וכל התשואה נוצרה ברבעון השני.\n* Millennium Management: שתי יחידות מסחר סביב איזוני מדדים הרוויחו כ-3.7 מיליארד דולר. Millennium עלתה 4.1% ביוני ותשואתה מתחילת השנה עומדת על 10.5%, כאשר הצוותים ייצרו יותר ממחצית מהרווח החודשי לפני עמלות, כ-6.6 מיליארד דולר."
    }
  ]
}
